minytube/__init__.py
minytube/channel.py
minytube/deferred_generator_list.py
minytube/disk_cache.py
minytube/filter_.py
minytube/globals_.py
minytube/http_client.py
minytube/innertube.py
minytube/json_extractor.py
minytube/multi_fetcher.py
minytube/playlist.py
minytube/search.py
minytube/subtitles.py
minytube/youtube.py
minytube-0.1.0.dist-info/LICENSE
minytube-0.1.0.dist-info/METADATA
minytube-0.1.0.dist-info/WHEEL
minytube-0.1.0.dist-info/top_level.txt
minytube-0.1.0.dist-info/RECORD
