Metadata-Version: 2.1
Name: minytube
Version: 0.1.0
Summary: A minimal YouTube library example with caching, search, etc.
Home-page: https://github.com/bes-dev/minytube
Author: Sergei Belousov aka BeS
Author-email: sergei.o.belousov@gmail.com
License: UNKNOWN
Platform: UNKNOWN
Requires-Python: >=3.7
License-File: LICENSE
Requires-Dist: beautifulsoup4>=4.13.0
Requires-Dist: requests>=2.32.3
